{
  "protocol_version" : "0.0.6",
  "configuration" : {
    "version" : "(6.13.0) (explicit/2e83cbd7)",
    "tlc" : "__thread",
    "sigsgev" : "normal",
    "notifications" : "kqueue",
    "architecture" : "arm64",
    "disabled_features" : "com,shared_perfcounters",
    "smallconfig" : "disabled",
    "bigarrays" : "disabled",
    "softdebug" : "enabled",
    "interpreter" : "enabled",
    "llvm_support" : "disabled",
    "suspend" : "preemptive"
  },
  "memory" : {
    "Resident Size" : "1044119552",
    "Virtual Size" : "422593478656",
    "minor_gc_time" : "0",
    "major_gc_time" : "690353",
    "minor_gc_count" : "0",
    "major_gc_count" : "11",
    "major_gc_time_concurrent" : "0"
 },
  "threads" : [
 {
    "is_managed" : false,
    "offset_free_hash" : "0x0",
    "offset_rich_hash" : "0x0",
    "crashed" : false,
    "native_thread_id" : "0x178c47000",
    "thread_info_addr" : "0x1389fa400",
    "thread_name" : "Debugger agent",
    "ctx" : {
      "IP" : "0x190064808",
      "SP" : "0x178c46aa0",
      "BP" : "0x178c46ae0"
  },
    "unmanaged_frames" : [
  {
      "is_managed" : "false",
      "native_address" : "0x153104b5c",
      "native_offset" : "0x00000"
   }
,
  {
      "is_managed" : "false",
      "native_address" : "0x15323c5bc",
      "native_offset" : "0x00000"
   }
,
  {
      "is_managed" : "false",
      "native_address" : "0x15323c918",
      "native_offset" : "0x00000"
   }
,
  {
      "is_managed" : "false",
      "native_address" : "0x15323c6e0",
      "native_offset" : "0x00000"
   }
,
  {
      "is_managed" : "false",
      "native_address" : "0x153145b70",
      "native_offset" : "0x00000"
   }
,
  {
      "is_managed" : "false",
      "native_address" : "0x1900caa84",
      "native_offset" : "0x00000"
   }
,
  {
      "is_managed" : "false",
      "native_address" : "0x1531748b4",
      "native_offset" : "0x00000"
   }
,
  {
      "is_managed" : "false",
      "native_address" : "0x15316b4b0",
      "native_offset" : "0x00000"
   }
,
  {
      "is_managed" : "false",
      "native_address" : "0x15323d328",
      "native_offset" : "0x00000"
   }
,
  {
      "is_managed" : "false",
      "native_address" : "0x15323d1d4",
      "native_offset" : "0x00000"
   }
,
  {
      "is_managed" : "false",
      "native_address" : "0x1532bcc00",
      "native_offset" : "0x00000"
   }
,
  {
      "is_managed" : "false",
      "native_address" : "0x1532bcb88",
      "native_offset" : "0x00000"
   }
,
  {
      "is_managed" : "false",
      "native_address" : "0x19009bfa8",
      "native_offset" : "0x00000"
   }
,
  {
      "is_managed" : "false",
      "native_address" : "0x190096da0",
      "native_offset" : "0x00000"
   }

  ]
 },
 {
    "is_managed" : false,
    "offset_free_hash" : "0x0",
    "offset_rich_hash" : "0x0",
    "crashed" : false,
    "native_thread_id" : "0x30458f000",
    "thread_info_addr" : "0x1388ef400",
    "thread_name" : "Thread Pool Worker",
    "ctx" : {
      "IP" : "0x19005bea8",
      "SP" : "0x30458edb0",
      "BP" : "0x30458ee50"
  },
    "unmanaged_frames" : [
  {
      "is_managed" : "false",
      "native_address" : "0x153104b5c",
      "native_offset" : "0x00000"
   }
,
  {
      "is_managed" : "false",
      "native_address" : "0x15323c5bc",
      "native_offset" : "0x00000"
   }
,
  {
      "is_managed" : "false",
      "native_address" : "0x15323c918",
      "native_offset" : "0x00000"
   }
,
  {
      "is_managed" : "false",
      "native_address" : "0x15323c6e0",
      "native_offset" : "0x00000"
   }
,
  {
      "is_managed" : "false",
      "native_address" : "0x153145b70",
      "native_offset" : "0x00000"
   }
,
  {
      "is_managed" : "false",
      "native_address" : "0x1900caa84",
      "native_offset" : "0x00000"
   }
,
  {
      "is_managed" : "false",
      "native_address" : "0x15319490c",
      "native_offset" : "0x00000"
   }
,
  {
      "is_managed" : "false",
      "native_address" : "0x15323d328",
      "native_offset" : "0x00000"
   }
,
  {
      "is_managed" : "false",
      "native_address" : "0x15323d1d4",
      "native_offset" : "0x00000"
   }
,
  {
      "is_managed" : "false",
      "native_address" : "0x1532bcc00",
      "native_offset" : "0x00000"
   }
,
  {
      "is_managed" : "false",
      "native_address" : "0x1532bcb88",
      "native_offset" : "0x00000"
   }
,
  {
      "is_managed" : "false",
      "native_address" : "0x19009bfa8",
      "native_offset" : "0x00000"
   }
,
  {
      "is_managed" : "false",
      "native_address" : "0x190096da0",
      "native_offset" : "0x00000"
   }

  ]
 },
 {
    "is_managed" : false,
    "offset_free_hash" : "0x0",
    "offset_rich_hash" : "0x0",
    "crashed" : false,
    "native_thread_id" : "0x17a9d7000",
    "thread_info_addr" : "0x148811e00",
    "thread_name" : "Thread Pool Worker",
    "ctx" : {
      "IP" : "0x19005bea8",
      "SP" : "0x17a9d6db0",
      "BP" : "0x17a9d6e50"
  },
    "unmanaged_frames" : [
  {
      "is_managed" : "false",
      "native_address" : "0x153104b5c",
      "native_offset" : "0x00000"
   }
,
  {
      "is_managed" : "false",
      "native_address" : "0x15323c5bc",
      "native_offset" : "0x00000"
   }
,
  {
      "is_managed" : "false",
      "native_address" : "0x15323c918",
      "native_offset" : "0x00000"
   }
,
  {
      "is_managed" : "false",
      "native_address" : "0x15323c6e0",
      "native_offset" : "0x00000"
   }
,
  {
      "is_managed" : "false",
      "native_address" : "0x153145b70",
      "native_offset" : "0x00000"
   }
,
  {
      "is_managed" : "false",
      "native_address" : "0x1900caa84",
      "native_offset" : "0x00000"
   }
,
  {
      "is_managed" : "false",
      "native_address" : "0x15319490c",
      "native_offset" : "0x00000"
   }
,
  {
      "is_managed" : "false",
      "native_address" : "0x15323d328",
      "native_offset" : "0x00000"
   }
,
  {
      "is_managed" : "false",
      "native_address" : "0x15323d1d4",
      "native_offset" : "0x00000"
   }
,
  {
      "is_managed" : "false",
      "native_address" : "0x1532bcc00",
      "native_offset" : "0x00000"
   }
,
  {
      "is_managed" : "false",
      "native_address" : "0x1532bcb88",
      "native_offset" : "0x00000"
   }
,
  {
      "is_managed" : "false",
      "native_address" : "0x19009bfa8",
      "native_offset" : "0x00000"
   }
,
  {
      "is_managed" : "false",
      "native_address" : "0x190096da0",
      "native_offset" : "0x00000"
   }

  ]
 },
 {
    "is_managed" : false,
    "offset_free_hash" : "0x0",
    "offset_rich_hash" : "0x0",
    "crashed" : false,
    "native_thread_id" : "0x1792f7000",
    "thread_info_addr" : "0x179b29600",
    "thread_name" : "tid_2333b",
    "ctx" : {
      "IP" : "0x19005f710",
      "SP" : "0x1792f6c20",
      "BP" : "0x1792f6cb0"
  },
    "unmanaged_frames" : [
  {
      "is_managed" : "false",
      "native_address" : "0x153104b5c",
      "native_offset" : "0x00000"
   }
,
  {
      "is_managed" : "false",
      "native_address" : "0x15323c5bc",
      "native_offset" : "0x00000"
   }
,
  {
      "is_managed" : "false",
      "native_address" : "0x15323c918",
      "native_offset" : "0x00000"
   }
,
  {
      "is_managed" : "false",
      "native_address" : "0x15323c6e0",
      "native_offset" : "0x00000"
   }
,
  {
      "is_managed" : "false",
      "native_address" : "0x153145b70",
      "native_offset" : "0x00000"
   }
,
  {
      "is_managed" : "false",
      "native_address" : "0x1900caa84",
      "native_offset" : "0x00000"
   }
,
  {
      "is_managed" : "false",
      "native_address" : "0x19009c5a0",
      "native_offset" : "0x00000"
   }
,
  {
      "is_managed" : "false",
      "native_address" : "0x15328bd58",
      "native_offset" : "0x00000"
   }
,
  {
      "is_managed" : "false",
      "native_address" : "0x153295a34",
      "native_offset" : "0x00000"
   }
,
  {
      "is_managed" : "false",
      "native_address" : "0x153194114",
      "native_offset" : "0x00000"
   }
,
  {
      "is_managed" : "false",
      "native_address" : "0x15323d328",
      "native_offset" : "0x00000"
   }
,
  {
      "is_managed" : "false",
      "native_address" : "0x15323d1d4",
      "native_offset" : "0x00000"
   }
,
  {
      "is_managed" : "false",
      "native_address" : "0x1532bcc00",
      "native_offset" : "0x00000"
   }
,
  {
      "is_managed" : "false",
      "native_address" : "0x1532bcb88",
      "native_offset" : "0x00000"
   }
,
  {
      "is_managed" : "false",
      "native_address" : "0x19009bfa8",
      "native_offset" : "0x00000"
   }
,
  {
      "is_managed" : "false",
      "native_address" : "0x190096da0",
      "native_offset" : "0x00000"
   }

  ]
 },
 {
    "is_managed" : false,
    "offset_free_hash" : "0x0",
    "offset_rich_hash" : "0x0",
    "crashed" : true,
    "native_thread_id" : "0x1eb509b40",
    "thread_info_addr" : "0x1388d7e00",
    "thread_name" : "tid_103",
    "ctx" : {
      "IP" : "0x104db5a94",
      "SP" : "0x16db09690",
      "BP" : "0x16db096b0"
  },
    "unmanaged_frames" : [
  {
      "is_managed" : "false",
      "native_address" : "0x153104b5c",
      "native_offset" : "0x00000"
   }
,
  {
      "is_managed" : "false",
      "native_address" : "0x15323c5bc",
      "native_offset" : "0x00000"
   }
,
  {
      "is_managed" : "false",
      "native_address" : "0x15323c918",
      "native_offset" : "0x00000"
   }
,
  {
      "is_managed" : "false",
      "native_address" : "0x15323cf08",
      "native_offset" : "0x00000"
   }
,
  {
      "is_managed" : "false",
      "native_address" : "0x1531469bc",
      "native_offset" : "0x00000"
   }
,
  {
      "is_managed" : "false",
      "native_address" : "0x153108cf4",
      "native_offset" : "0x00000"
   }
,
  {
      "is_managed" : "false",
      "native_address" : "0x1530915e4",
      "native_offset" : "0x00000"
   }
,
  {
      "is_managed" : "false",
      "native_address" : "0x1900caa84",
      "native_offset" : "0x00000"
   }
,
  {
      "is_managed" : "false",
      "native_address" : "0x104db5948",
      "native_offset" : "0x00000"
   }
,
  {
      "is_managed" : "false",
      "native_address" : "0x1934fec3c",
      "native_offset" : "0x00000"
   }
,
  {
      "is_managed" : "false",
      "native_address" : "0x193608afc",
      "native_offset" : "0x00000"
   }
,
  {
      "is_managed" : "false",
      "native_address" : "0x1935f3d3c",
      "native_offset" : "0x00000"
   }
,
  {
      "is_managed" : "false",
      "native_address" : "0x1999863b0",
      "native_offset" : "0x00000"
   }
,
  {
      "is_managed" : "false",
      "native_address" : "0x199985834",
      "native_offset" : "0x00000"
   }
,
  {
      "is_managed" : "false",
      "native_address" : "0x19999ba4c",
      "native_offset" : "0x00000"
   }
,
  {
      "is_managed" : "false",
      "native_address" : "0x1999f9810",
      "native_offset" : "0x00000"
   }
,
  {
      "is_managed" : "false",
      "native_address" : "0x199a08358",
      "native_offset" : "0x00000"
   }
,
  {
      "is_managed" : "false",
      "native_address" : "0x19998201c",
      "native_offset" : "0x00000"
   }
,
  {
      "is_managed" : "false",
      "native_address" : "0x1999863b0",
      "native_offset" : "0x00000"
   }
,
  {
      "is_managed" : "false",
      "native_address" : "0x199985834",
      "native_offset" : "0x00000"
   }
,
  {
      "is_managed" : "false",
      "native_address" : "0x19999ba4c",
      "native_offset" : "0x00000"
   }
,
  {
      "is_managed" : "false",
      "native_address" : "0x199b507bc",
      "native_offset" : "0x00000"
   }
,
  {
      "is_managed" : "false",
      "native_address" : "0x199a07c90",
      "native_offset" : "0x00000"
   }
,
  {
      "is_managed" : "false",
      "native_address" : "0x199b4deb4",
      "native_offset" : "0x00000"
   }
,
  {
      "is_managed" : "false",
      "native_address" : "0x1cc0671e0",
      "native_offset" : "0x00000"
   }
,
  {
      "is_managed" : "false",
      "native_address" : "0x1cc067200",
      "native_offset" : "0x00000"
   }
,
  {
      "is_managed" : "false",
      "native_address" : "0x1cc066e80",
      "native_offset" : "0x00000"
   }
,
  {
      "is_managed" : "false",
      "native_address" : "0x1cc066ca0",
      "native_offset" : "0x00000"
   }
,
  {
      "is_managed" : "false",
      "native_address" : "0x1cc0682b4",
      "native_offset" : "0x00000"
   }
,
  {
      "is_managed" : "false",
      "native_address" : "0x19016f254",
      "native_offset" : "0x00000"
   }
,
  {
      "is_managed" : "false",
      "native_address" : "0x19020af30",
      "native_offset" : "0x00000"
   }
,
  {
      "is_managed" : "false",
      "native_address" : "0x19020ae78",
      "native_offset" : "0x00000"
   }
,
  {
      "is_managed" : "false",
      "native_address" : "0x190140580",
      "native_offset" : "0x00000"
   }
,
  {
      "is_managed" : "false",
      "native_address" : "0x19109d9e4",
      "native_offset" : "0x00000"
   }
,
  {
      "is_managed" : "false",
      "native_address" : "0x19016f254",
      "native_offset" : "0x00000"
   }
,
  {
      "is_managed" : "false",
      "native_address" : "0x19020af30",
      "native_offset" : "0x00000"
   }
,
  {
      "is_managed" : "false",
      "native_address" : "0x19020ae78",
      "native_offset" : "0x00000"
   }
,
  {
      "is_managed" : "false",
      "native_address" : "0x190140580",
      "native_offset" : "0x00000"
   }
,
  {
      "is_managed" : "false",
      "native_address" : "0x19109d9e4",
      "native_offset" : "0x00000"
   }
,
  {
      "is_managed" : "false",
      "native_address" : "0x19354af34",
      "native_offset" : "0x00000"
   }
,
  {
      "is_managed" : "false",
      "native_address" : "0x193548cf4",
      "native_offset" : "0x00000"
   }
,
  {
      "is_managed" : "false",
      "native_address" : "0x1942f8618",
      "native_offset" : "0x00000"
   }
,
  {
      "is_managed" : "false",
      "native_address" : "0x19354842c",
      "native_offset" : "0x00000"
   }
,
  {
      "is_managed" : "false",
      "native_address" : "0x193547ff4",
      "native_offset" : "0x00000"
   }
,
  {
      "is_managed" : "false",
      "native_address" : "0x193c9e610",
      "native_offset" : "0x00000"
   }
,
  {
      "is_managed" : "false",
      "native_address" : "0x193547f44",
      "native_offset" : "0x00000"
   }
,
  {
      "is_managed" : "false",
      "native_address" : "0x193547db0",
      "native_offset" : "0x00000"
   }
,
  {
      "is_managed" : "false",
      "native_address" : "0x193c9dde8",
      "native_offset" : "0x00000"
   }
,
  {
      "is_managed" : "false",
      "native_address" : "0x1935479a8",
      "native_offset" : "0x00000"
   }
,
  {
      "is_managed" : "false",
      "native_address" : "0x1935478f4",
      "native_offset" : "0x00000"
   }
,
  {
      "is_managed" : "false",
      "native_address" : "0x193546e68",
      "native_offset" : "0x00000"
   }
,
  {
      "is_managed" : "false",
      "native_address" : "0x193546610",
      "native_offset" : "0x00000"
   }
,
  {
      "is_managed" : "false",
      "native_address" : "0x1999863b0",
      "native_offset" : "0x00000"
   }
,
  {
      "is_managed" : "false",
      "native_address" : "0x199985834",
      "native_offset" : "0x00000"
   }
,
  {
      "is_managed" : "false",
      "native_address" : "0x1999856c4",
      "native_offset" : "0x00000"
   }
,
  {
      "is_managed" : "false",
      "native_address" : "0x1999e2900",
      "native_offset" : "0x00000"
   }
,
  {
      "is_managed" : "false",
      "native_address" : "0x1999e2e50",
      "native_offset" : "0x00000"
   }
,
  {
      "is_managed" : "false",
      "native_address" : "0x1999e2c5c",
      "native_offset" : "0x00000"
   }
,
  {
      "is_managed" : "false",
      "native_address" : "0x1999e2958",
      "native_offset" : "0x00000"
   }
,
  {
      "is_managed" : "false",
      "native_address" : "0x1999e2708",
      "native_offset" : "0x00000"
   }
,
  {
      "is_managed" : "false",
      "native_address" : "0x1999e233c",
      "native_offset" : "0x00000"
   }
,
  {
      "is_managed" : "false",
      "native_address" : "0x1999e20c8",
      "native_offset" : "0x00000"
   }
,
  {
      "is_managed" : "false",
      "native_address" : "0x1999e1e4c",
      "native_offset" : "0x00000"
   }
,
  {
      "is_managed" : "false",
      "native_address" : "0x1999e1cb0",
      "native_offset" : "0x00000"
   }
,
  {
      "is_managed" : "false",
      "native_address" : "0x1999e1a40",
      "native_offset" : "0x00000"
   }
,
  {
      "is_managed" : "false",
      "native_address" : "0x1999e1858",
      "native_offset" : "0x00000"
   }
,
  {
      "is_managed" : "false",
      "native_address" : "0x1999e1538",
      "native_offset" : "0x00000"
   }
,
  {
      "is_managed" : "false",
      "native_address" : "0x1999e1244",
      "native_offset" : "0x00000"
   }
,
  {
      "is_managed" : "false",
      "native_address" : "0x1999ceed0",
      "native_offset" : "0x00000"
   }
,
  {
      "is_managed" : "false",
      "native_address" : "0x193ca24f0",
      "native_offset" : "0x00000"
   }
,
  {
      "is_managed" : "false",
      "native_address" : "0x193ca21cc",
      "native_offset" : "0x00000"
   }
,
  {
      "is_managed" : "false",
      "native_address" : "0x1935453c4",
      "native_offset" : "0x00000"
   }
,
  {
      "is_managed" : "false",
      "native_address" : "0x193544df0",
      "native_offset" : "0x00000"
   }
,
  {
      "is_managed" : "false",
      "native_address" : "0x193544800",
      "native_offset" : "0x00000"
   }
,
  {
      "is_managed" : "false",
      "native_address" : "0x193544658",
      "native_offset" : "0x00000"
   }
,
  {
      "is_managed" : "false",
      "native_address" : "0x1935444ac",
      "native_offset" : "0x00000"
   }
,
  {
      "is_managed" : "false",
      "native_address" : "0x1934c5150",
      "native_offset" : "0x00000"
   }
,
  {
      "is_managed" : "false",
      "native_address" : "0x1934c4d9c",
      "native_offset" : "0x00000"
   }
,
  {
      "is_managed" : "false",
      "native_address" : "0x19390e320",
      "native_offset" : "0x00000"
   }
,
  {
      "is_managed" : "false",
      "native_address" : "0x193beca7c",
      "native_offset" : "0x00000"
   }

  ]
 },
 {
    "is_managed" : true,
    "offset_free_hash" : "0xf032b1408",
    "offset_rich_hash" : "0xf032b158e",
    "crashed" : false,
    "native_thread_id" : "0x2e8c07000",
    "thread_info_addr" : "0x138251e00",
    "thread_name" : "ServerSocket-UnityServer-Sender",
    "ctx" : {
      "IP" : "0x19005f710",
      "SP" : "0x2e8c06350",
      "BP" : "0x2e8c063e0"
  },
    "managed_frames" : [
  {
      "is_managed" : "false",
      "native_address" : "unregistered"
   }
,
  {
      "is_managed" : "true",
      "guid" : "4FDEFFDA-907B-4817-9650-7BEE174BE5E3",
      "token" : "0x00000",
      "native_offset" : "0x0",
      "filename" : "mscorlib.dll",
      "sizeofimage" : "0x470000",
      "timestamp" : "0xcfa2eafc",
      "il_offset" : "0xffffffff"
   }
,
  {
      "is_managed" : "true",
      "guid" : "4FDEFFDA-907B-4817-9650-7BEE174BE5E3",
      "token" : "0x6001f5d",
      "native_offset" : "0x0",
      "filename" : "mscorlib.dll",
      "sizeofimage" : "0x470000",
      "timestamp" : "0xcfa2eafc",
      "il_offset" : "0x0002f"
   }
,
  {
      "is_managed" : "true",
      "guid" : "4FDEFFDA-907B-4817-9650-7BEE174BE5E3",
      "token" : "0x6001f50",
      "native_offset" : "0x0",
      "filename" : "mscorlib.dll",
      "sizeofimage" : "0x470000",
      "timestamp" : "0xcfa2eafc",
      "il_offset" : "0x0000e"
   }
,
  {
      "is_managed" : "true",
      "guid" : "4FDEFFDA-907B-4817-9650-7BEE174BE5E3",
      "token" : "0x6001f54",
      "native_offset" : "0x0",
      "filename" : "mscorlib.dll",
      "sizeofimage" : "0x470000",
      "timestamp" : "0xcfa2eafc",
      "il_offset" : "0x00000"
   }
,
  {
      "is_managed" : "true",
      "guid" : "A26E6BA7-6929-460A-ADBD-68434ABE4966",
      "token" : "0x60003be",
      "native_offset" : "0x0",
      "filename" : "JetBrains.Rider.Unity.Editor.Plugin.Net46.Repacked",
      "sizeofimage" : "0x8e000",
      "timestamp" : "0x0",
      "il_offset" : "0x0002d"
   }
,
  {
      "is_managed" : "true",
      "guid" : "A26E6BA7-6929-460A-ADBD-68434ABE4966",
      "token" : "0x60003bb",
      "native_offset" : "0x0",
      "filename" : "JetBrains.Rider.Unity.Editor.Plugin.Net46.Repacked",
      "sizeofimage" : "0x8e000",
      "timestamp" : "0x0",
      "il_offset" : "0x00000"
   }
,
  {
      "is_managed" : "true",
      "guid" : "4FDEFFDA-907B-4817-9650-7BEE174BE5E3",
      "token" : "0x6001f7d",
      "native_offset" : "0x0",
      "filename" : "mscorlib.dll",
      "sizeofimage" : "0x470000",
      "timestamp" : "0xcfa2eafc",
      "il_offset" : "0x00014"
   }
,
  {
      "is_managed" : "true",
      "guid" : "4FDEFFDA-907B-4817-9650-7BEE174BE5E3",
      "token" : "0x6001f25",
      "native_offset" : "0x0",
      "filename" : "mscorlib.dll",
      "sizeofimage" : "0x470000",
      "timestamp" : "0xcfa2eafc",
      "il_offset" : "0x00071"
   }
,
  {
      "is_managed" : "true",
      "guid" : "4FDEFFDA-907B-4817-9650-7BEE174BE5E3",
      "token" : "0x6001f23",
      "native_offset" : "0x0",
      "filename" : "mscorlib.dll",
      "sizeofimage" : "0x470000",
      "timestamp" : "0xcfa2eafc",
      "il_offset" : "0x00000"
   }
,
  {
      "is_managed" : "true",
      "guid" : "4FDEFFDA-907B-4817-9650-7BEE174BE5E3",
      "token" : "0x6001f22",
      "native_offset" : "0x0",
      "filename" : "mscorlib.dll",
      "sizeofimage" : "0x470000",
      "timestamp" : "0xcfa2eafc",
      "il_offset" : "0x0002b"
   }
,
  {
      "is_managed" : "true",
      "guid" : "4FDEFFDA-907B-4817-9650-7BEE174BE5E3",
      "token" : "0x6001f7f",
      "native_offset" : "0x0",
      "filename" : "mscorlib.dll",
      "sizeofimage" : "0x470000",
      "timestamp" : "0xcfa2eafc",
      "il_offset" : "0x00008"
   }
,
  {
      "is_managed" : "true",
      "guid" : "4FDEFFDA-907B-4817-9650-7BEE174BE5E3",
      "token" : "0x00000",
      "native_offset" : "0x0",
      "filename" : "mscorlib.dll",
      "sizeofimage" : "0x470000",
      "timestamp" : "0xcfa2eafc",
      "il_offset" : "0x00065"
   }

  ],
  "unmanaged_frames" : [
 {
    "is_managed" : "false",
    "native_address" : "0x153104b5c",
    "native_offset" : "0x00000"
  }
,
 {
    "is_managed" : "false",
    "native_address" : "0x15323c5bc",
    "native_offset" : "0x00000"
  }
,
 {
    "is_managed" : "false",
    "native_address" : "0x15323c918",
    "native_offset" : "0x00000"
  }
,
 {
    "is_managed" : "false",
    "native_address" : "0x15323c6e0",
    "native_offset" : "0x00000"
  }
,
 {
    "is_managed" : "false",
    "native_address" : "0x153145b70",
    "native_offset" : "0x00000"
  }
,
 {
    "is_managed" : "false",
    "native_address" : "0x1900caa84",
    "native_offset" : "0x00000"
  }
,
 {
    "is_managed" : "false",
    "native_address" : "0x19009c574",
    "native_offset" : "0x00000"
  }
,
 {
    "is_managed" : "false",
    "native_address" : "0x15328bd80",
    "native_offset" : "0x00000"
  }
,
 {
    "is_managed" : "false",
    "native_address" : "0x1532482ec",
    "native_offset" : "0x00000"
  }
,
 {
    "is_managed" : "false",
    "native_address" : "0x153248120",
    "native_offset" : "0x00000"
  }
,
 {
    "is_managed" : "false",
    "native_address" : "0x1532774c0",
    "native_offset" : "0x00000"
  }
,
 {
    "is_managed" : "false",
    "native_address" : "0x1531e0944",
    "native_offset" : "0x00000"
  }
,
 {
    "is_managed" : "true",
    "guid" : "4FDEFFDA-907B-4817-9650-7BEE174BE5E3",
    "token" : "0x00000",
    "native_offset" : "0x0",
    "filename" : "mscorlib.dll",
    "sizeofimage" : "0x470000",
    "timestamp" : "0xcfa2eafc",
    "il_offset" : "0x00000"
  }
,
 {
    "is_managed" : "true",
    "guid" : "4FDEFFDA-907B-4817-9650-7BEE174BE5E3",
    "token" : "0x6001f5d",
    "native_offset" : "0x0",
    "filename" : "mscorlib.dll",
    "sizeofimage" : "0x470000",
    "timestamp" : "0xcfa2eafc",
    "il_offset" : "0x00000"
  }
,
 {
    "is_managed" : "true",
    "guid" : "4FDEFFDA-907B-4817-9650-7BEE174BE5E3",
    "token" : "0x6001f50",
    "native_offset" : "0x0",
    "filename" : "mscorlib.dll",
    "sizeofimage" : "0x470000",
    "timestamp" : "0xcfa2eafc",
    "il_offset" : "0x00000"
  }
,
 {
    "is_managed" : "true",
    "guid" : "4FDEFFDA-907B-4817-9650-7BEE174BE5E3",
    "token" : "0x6001f54",
    "native_offset" : "0x0",
    "filename" : "mscorlib.dll",
    "sizeofimage" : "0x470000",
    "timestamp" : "0xcfa2eafc",
    "il_offset" : "0x00000"
  }
,
 {
    "is_managed" : "true",
    "guid" : "A26E6BA7-6929-460A-ADBD-68434ABE4966",
    "token" : "0x60003be",
    "native_offset" : "0x0",
    "filename" : "JetBrains.Rider.Unity.Editor.Plugin.Net46.Repacked",
    "sizeofimage" : "0x8e000",
    "timestamp" : "0x0",
    "il_offset" : "0x00000"
  }
,
 {
    "is_managed" : "true",
    "guid" : "A26E6BA7-6929-460A-ADBD-68434ABE4966",
    "token" : "0x60003bb",
    "native_offset" : "0x0",
    "filename" : "JetBrains.Rider.Unity.Editor.Plugin.Net46.Repacked",
    "sizeofimage" : "0x8e000",
    "timestamp" : "0x0",
    "il_offset" : "0x00000"
  }
,
 {
    "is_managed" : "true",
    "guid" : "4FDEFFDA-907B-4817-9650-7BEE174BE5E3",
    "token" : "0x6001f7d",
    "native_offset" : "0x0",
    "filename" : "mscorlib.dll",
    "sizeofimage" : "0x470000",
    "timestamp" : "0xcfa2eafc",
    "il_offset" : "0x00000"
  }
,
 {
    "is_managed" : "true",
    "guid" : "4FDEFFDA-907B-4817-9650-7BEE174BE5E3",
    "token" : "0x6001f25",
    "native_offset" : "0x0",
    "filename" : "mscorlib.dll",
    "sizeofimage" : "0x470000",
    "timestamp" : "0xcfa2eafc",
    "il_offset" : "0x00000"
  }
,
 {
    "is_managed" : "true",
    "guid" : "4FDEFFDA-907B-4817-9650-7BEE174BE5E3",
    "token" : "0x6001f23",
    "native_offset" : "0x0",
    "filename" : "mscorlib.dll",
    "sizeofimage" : "0x470000",
    "timestamp" : "0xcfa2eafc",
    "il_offset" : "0x00000"
  }
,
 {
    "is_managed" : "true",
    "guid" : "4FDEFFDA-907B-4817-9650-7BEE174BE5E3",
    "token" : "0x6001f22",
    "native_offset" : "0x0",
    "filename" : "mscorlib.dll",
    "sizeofimage" : "0x470000",
    "timestamp" : "0xcfa2eafc",
    "il_offset" : "0x00000"
  }
,
 {
    "is_managed" : "true",
    "guid" : "4FDEFFDA-907B-4817-9650-7BEE174BE5E3",
    "token" : "0x6001f7f",
    "native_offset" : "0x0",
    "filename" : "mscorlib.dll",
    "sizeofimage" : "0x470000",
    "timestamp" : "0xcfa2eafc",
    "il_offset" : "0x00000"
  }
,
 {
    "is_managed" : "true",
    "guid" : "4FDEFFDA-907B-4817-9650-7BEE174BE5E3",
    "token" : "0x00000",
    "native_offset" : "0x0",
    "filename" : "mscorlib.dll",
    "sizeofimage" : "0x470000",
    "timestamp" : "0xcfa2eafc",
    "il_offset" : "0x00000"
  }
,
 {
    "is_managed" : "false",
    "native_address" : "0x1530948a4",
    "native_offset" : "0x00000"
  }
,
 {
    "is_managed" : "false",
    "native_address" : "0x15321b45c",
    "native_offset" : "0x00000"
  }
,
 {
    "is_managed" : "false",
    "native_address" : "0x15321d058",
    "native_offset" : "0x00000"
  }
,
 {
    "is_managed" : "false",
    "native_address" : "0x15323d41c",
    "native_offset" : "0x00000"
  }
,
 {
    "is_managed" : "false",
    "native_address" : "0x15323d1d4",
    "native_offset" : "0x00000"
  }
,
 {
    "is_managed" : "false",
    "native_address" : "0x1532bcc00",
    "native_offset" : "0x00000"
  }
,
 {
    "is_managed" : "false",
    "native_address" : "0x1532bcb88",
    "native_offset" : "0x00000"
  }
,
 {
    "is_managed" : "false",
    "native_address" : "0x19009bfa8",
    "native_offset" : "0x00000"
  }
,
 {
    "is_managed" : "false",
    "native_address" : "0x190096da0",
    "native_offset" : "0x00000"
  }

 ]
},
{
  "is_managed" : true,
  "offset_free_hash" : "0xd8fc96b28",
  "offset_rich_hash" : "0xd8fc96c89",
  "crashed" : false,
  "native_thread_id" : "0x2e8e13000",
  "thread_info_addr" : "0x2c1250a00",
  "thread_name" : "ServerSocket-UnityServer-Receiver",
  "ctx" : {
    "IP" : "0x190064808",
    "SP" : "0x2e8e125f0",
    "BP" : "0x2e8e12660"
 },
  "managed_frames" : [
 {
    "is_managed" : "false",
    "native_address" : "unregistered"
  }
,
 {
    "is_managed" : "true",
    "guid" : "5E85BD56-D233-48EA-A9AD-D61F3D934F9C",
    "token" : "0x00000",
    "native_offset" : "0x0",
    "filename" : "System.dll",
    "sizeofimage" : "0x29a000",
    "timestamp" : "0xad5e3819",
    "il_offset" : "0xffffffff"
  }
,
 {
    "is_managed" : "true",
    "guid" : "5E85BD56-D233-48EA-A9AD-D61F3D934F9C",
    "token" : "0x6002b41",
    "native_offset" : "0x0",
    "filename" : "System.dll",
    "sizeofimage" : "0x29a000",
    "timestamp" : "0xad5e3819",
    "il_offset" : "0x0000c"
  }
,
 {
    "is_managed" : "true",
    "guid" : "5E85BD56-D233-48EA-A9AD-D61F3D934F9C",
    "token" : "0x6002b3a",
    "native_offset" : "0x0",
    "filename" : "System.dll",
    "sizeofimage" : "0x29a000",
    "timestamp" : "0xad5e3819",
    "il_offset" : "0x00008"
  }
,
 {
    "is_managed" : "true",
    "guid" : "A26E6BA7-6929-460A-ADBD-68434ABE4966",
    "token" : "0x6000e5f",
    "native_offset" : "0x0",
    "filename" : "JetBrains.Rider.Unity.Editor.Plugin.Net46.Repacked",
    "sizeofimage" : "0x8e000",
    "timestamp" : "0x0",
    "il_offset" : "0x00031"
  }
,
 {
    "is_managed" : "true",
    "guid" : "A26E6BA7-6929-460A-ADBD-68434ABE4966",
    "token" : "0x6000660",
    "native_offset" : "0x0",
    "filename" : "JetBrains.Rider.Unity.Editor.Plugin.Net46.Repacked",
    "sizeofimage" : "0x8e000",
    "timestamp" : "0x0",
    "il_offset" : "0x00000"
  }
,
 {
    "is_managed" : "true",
    "guid" : "A26E6BA7-6929-460A-ADBD-68434ABE4966",
    "token" : "0x6000e5e",
    "native_offset" : "0x0",
    "filename" : "JetBrains.Rider.Unity.Editor.Plugin.Net46.Repacked",
    "sizeofimage" : "0x8e000",
    "timestamp" : "0x0",
    "il_offset" : "0x00000"
  }
,
 {
    "is_managed" : "true",
    "guid" : "4FDEFFDA-907B-4817-9650-7BEE174BE5E3",
    "token" : "0x6001f7d",
    "native_offset" : "0x0",
    "filename" : "mscorlib.dll",
    "sizeofimage" : "0x470000",
    "timestamp" : "0xcfa2eafc",
    "il_offset" : "0x00014"
  }
,
 {
    "is_managed" : "true",
    "guid" : "4FDEFFDA-907B-4817-9650-7BEE174BE5E3",
    "token" : "0x6001f25",
    "native_offset" : "0x0",
    "filename" : "mscorlib.dll",
    "sizeofimage" : "0x470000",
    "timestamp" : "0xcfa2eafc",
    "il_offset" : "0x00071"
  }
,
 {
    "is_managed" : "true",
    "guid" : "4FDEFFDA-907B-4817-9650-7BEE174BE5E3",
    "token" : "0x6001f23",
    "native_offset" : "0x0",
    "filename" : "mscorlib.dll",
    "sizeofimage" : "0x470000",
    "timestamp" : "0xcfa2eafc",
    "il_offset" : "0x00000"
  }
,
 {
    "is_managed" : "true",
    "guid" : "4FDEFFDA-907B-4817-9650-7BEE174BE5E3",
    "token" : "0x6001f22",
    "native_offset" : "0x0",
    "filename" : "mscorlib.dll",
    "sizeofimage" : "0x470000",
    "timestamp" : "0xcfa2eafc",
    "il_offset" : "0x0002b"
  }
,
 {
    "is_managed" : "true",
    "guid" : "4FDEFFDA-907B-4817-9650-7BEE174BE5E3",
    "token" : "0x6001f7f",
    "native_offset" : "0x0",
    "filename" : "mscorlib.dll",
    "sizeofimage" : "0x470000",
    "timestamp" : "0xcfa2eafc",
    "il_offset" : "0x00008"
  }
,
 {
    "is_managed" : "true",
    "guid" : "4FDEFFDA-907B-4817-9650-7BEE174BE5E3",
    "token" : "0x00000",
    "native_offset" : "0x0",
    "filename" : "mscorlib.dll",
    "sizeofimage" : "0x470000",
    "timestamp" : "0xcfa2eafc",
    "il_offset" : "0x00065"
  }

 ],
"unmanaged_frames" : [
{
  "is_managed" : "false",
  "native_address" : "0x153104b5c",
  "native_offset" : "0x00000"
 }
,
{
  "is_managed" : "false",
  "native_address" : "0x15323c5bc",
  "native_offset" : "0x00000"
 }
,
{
  "is_managed" : "false",
  "native_address" : "0x15323c918",
  "native_offset" : "0x00000"
 }
,
{
  "is_managed" : "false",
  "native_address" : "0x15323c6e0",
  "native_offset" : "0x00000"
 }
,
{
  "is_managed" : "false",
  "native_address" : "0x153145b70",
  "native_offset" : "0x00000"
 }
,
{
  "is_managed" : "false",
  "native_address" : "0x1900caa84",
  "native_offset" : "0x00000"
 }
,
{
  "is_managed" : "false",
  "native_address" : "0x15318984c",
  "native_offset" : "0x00000"
 }
,
{
  "is_managed" : "false",
  "native_address" : "0x1532252a0",
  "native_offset" : "0x00000"
 }
,
{
  "is_managed" : "true",
  "guid" : "5E85BD56-D233-48EA-A9AD-D61F3D934F9C",
  "token" : "0x00000",
  "native_offset" : "0x0",
  "filename" : "System.dll",
  "sizeofimage" : "0x29a000",
  "timestamp" : "0xad5e3819",
  "il_offset" : "0x00000"
 }
,
{
  "is_managed" : "true",
  "guid" : "5E85BD56-D233-48EA-A9AD-D61F3D934F9C",
  "token" : "0x6002b41",
  "native_offset" : "0x0",
  "filename" : "System.dll",
  "sizeofimage" : "0x29a000",
  "timestamp" : "0xad5e3819",
  "il_offset" : "0x00000"
 }
,
{
  "is_managed" : "true",
  "guid" : "5E85BD56-D233-48EA-A9AD-D61F3D934F9C",
  "token" : "0x6002b3a",
  "native_offset" : "0x0",
  "filename" : "System.dll",
  "sizeofimage" : "0x29a000",
  "timestamp" : "0xad5e3819",
  "il_offset" : "0x00000"
 }
,
{
  "is_managed" : "true",
  "guid" : "A26E6BA7-6929-460A-ADBD-68434ABE4966",
  "token" : "0x6000e5f",
  "native_offset" : "0x0",
  "filename" : "JetBrains.Rider.Unity.Editor.Plugin.Net46.Repacked",
  "sizeofimage" : "0x8e000",
  "timestamp" : "0x0",
  "il_offset" : "0x00000"
 }
,
{
  "is_managed" : "true",
  "guid" : "A26E6BA7-6929-460A-ADBD-68434ABE4966",
  "token" : "0x6000660",
  "native_offset" : "0x0",
  "filename" : "JetBrains.Rider.Unity.Editor.Plugin.Net46.Repacked",
  "sizeofimage" : "0x8e000",
  "timestamp" : "0x0",
  "il_offset" : "0x00000"
 }
,
{
  "is_managed" : "true",
  "guid" : "A26E6BA7-6929-460A-ADBD-68434ABE4966",
  "token" : "0x6000e5e",
  "native_offset" : "0x0",
  "filename" : "JetBrains.Rider.Unity.Editor.Plugin.Net46.Repacked",
  "sizeofimage" : "0x8e000",
  "timestamp" : "0x0",
  "il_offset" : "0x00000"
 }
,
{
  "is_managed" : "true",
  "guid" : "4FDEFFDA-907B-4817-9650-7BEE174BE5E3",
  "token" : "0x6001f7d",
  "native_offset" : "0x0",
  "filename" : "mscorlib.dll",
  "sizeofimage" : "0x470000",
  "timestamp" : "0xcfa2eafc",
  "il_offset" : "0x00000"
 }
,
{
  "is_managed" : "true",
  "guid" : "4FDEFFDA-907B-4817-9650-7BEE174BE5E3",
  "token" : "0x6001f25",
  "native_offset" : "0x0",
  "filename" : "mscorlib.dll",
  "sizeofimage" : "0x470000",
  "timestamp" : "0xcfa2eafc",
  "il_offset" : "0x00000"
 }
,
{
  "is_managed" : "true",
  "guid" : "4FDEFFDA-907B-4817-9650-7BEE174BE5E3",
  "token" : "0x6001f23",
  "native_offset" : "0x0",
  "filename" : "mscorlib.dll",
  "sizeofimage" : "0x470000",
  "timestamp" : "0xcfa2eafc",
  "il_offset" : "0x00000"
 }
,
{
  "is_managed" : "true",
  "guid" : "4FDEFFDA-907B-4817-9650-7BEE174BE5E3",
  "token" : "0x6001f22",
  "native_offset" : "0x0",
  "filename" : "mscorlib.dll",
  "sizeofimage" : "0x470000",
  "timestamp" : "0xcfa2eafc",
  "il_offset" : "0x00000"
 }
,
{
  "is_managed" : "true",
  "guid" : "4FDEFFDA-907B-4817-9650-7BEE174BE5E3",
  "token" : "0x6001f7f",
  "native_offset" : "0x0",
  "filename" : "mscorlib.dll",
  "sizeofimage" : "0x470000",
  "timestamp" : "0xcfa2eafc",
  "il_offset" : "0x00000"
 }
,
{
  "is_managed" : "true",
  "guid" : "4FDEFFDA-907B-4817-9650-7BEE174BE5E3",
  "token" : "0x00000",
  "native_offset" : "0x0",
  "filename" : "mscorlib.dll",
  "sizeofimage" : "0x470000",
  "timestamp" : "0xcfa2eafc",
  "il_offset" : "0x00000"
 }
,
{
  "is_managed" : "false",
  "native_address" : "0x1530948a4",
  "native_offset" : "0x00000"
 }
,
{
  "is_managed" : "false",
  "native_address" : "0x15321b45c",
  "native_offset" : "0x00000"
 }
,
{
  "is_managed" : "false",
  "native_address" : "0x15321d058",
  "native_offset" : "0x00000"
 }
,
{
  "is_managed" : "false",
  "native_address" : "0x15323d41c",
  "native_offset" : "0x00000"
 }
,
{
  "is_managed" : "false",
  "native_address" : "0x15323d1d4",
  "native_offset" : "0x00000"
 }
,
{
  "is_managed" : "false",
  "native_address" : "0x1532bcc00",
  "native_offset" : "0x00000"
 }
,
{
  "is_managed" : "false",
  "native_address" : "0x1532bcb88",
  "native_offset" : "0x00000"
 }
,
{
  "is_managed" : "false",
  "native_address" : "0x19009bfa8",
  "native_offset" : "0x00000"
 }
,
{
  "is_managed" : "false",
  "native_address" : "0x190096da0",
  "native_offset" : "0x00000"
 }

]
},
{
"is_managed" : false,
"offset_free_hash" : "0x0",
"offset_rich_hash" : "0x0",
"crashed" : false,
"native_thread_id" : "0x2ec9c7000",
"thread_info_addr" : "0x2c17d5e00",
"thread_name" : "tid_26703",
"ctx" : {
  "IP" : "0x19005be90",
  "SP" : "0x2ec9c6d70",
  "BP" : "0x2ec9c6d80"
},
"unmanaged_frames" : [
{
  "is_managed" : "false",
  "native_address" : "0x153104b5c",
  "native_offset" : "0x00000"
 }
,
{
  "is_managed" : "false",
  "native_address" : "0x15323c5bc",
  "native_offset" : "0x00000"
 }
,
{
  "is_managed" : "false",
  "native_address" : "0x15323c918",
  "native_offset" : "0x00000"
 }
,
{
  "is_managed" : "false",
  "native_address" : "0x15323c6e0",
  "native_offset" : "0x00000"
 }
,
{
  "is_managed" : "false",
  "native_address" : "0x153145b70",
  "native_offset" : "0x00000"
 }
,
{
  "is_managed" : "false",
  "native_address" : "0x1900caa84",
  "native_offset" : "0x00000"
 }
,
{
  "is_managed" : "false",
  "native_address" : "0x18feec99c",
  "native_offset" : "0x00000"
 }
,
{
  "is_managed" : "false",
  "native_address" : "0x18feed050",
  "native_offset" : "0x00000"
 }
,
{
  "is_managed" : "false",
  "native_address" : "0x104e826b4",
  "native_offset" : "0x00000"
 }
,
{
  "is_managed" : "false",
  "native_address" : "0x10289e6fc",
  "native_offset" : "0x00000"
 }
,
{
  "is_managed" : "false",
  "native_address" : "0x102c81218",
  "native_offset" : "0x00000"
 }
,
{
  "is_managed" : "false",
  "native_address" : "0x102c811b4",
  "native_offset" : "0x00000"
 }
,
{
  "is_managed" : "false",
  "native_address" : "0x102e2c1e4",
  "native_offset" : "0x00000"
 }
,
{
  "is_managed" : "false",
  "native_address" : "0x19009bfa8",
  "native_offset" : "0x00000"
 }
,
{
  "is_managed" : "false",
  "native_address" : "0x190096da0",
  "native_offset" : "0x00000"
 }

]
},
{
"is_managed" : false,
"offset_free_hash" : "0x0",
"offset_rich_hash" : "0x0",
"crashed" : false,
"native_thread_id" : "0x17bddb000",
"thread_info_addr" : "0x13a28f400",
"thread_name" : "Thread Pool Worker",
"ctx" : {
  "IP" : "0x19005bea8",
  "SP" : "0x17bddadb0",
  "BP" : "0x17bddae50"
},
"unmanaged_frames" : [
{
  "is_managed" : "false",
  "native_address" : "0x153104b5c",
  "native_offset" : "0x00000"
 }
,
{
  "is_managed" : "false",
  "native_address" : "0x15323c5bc",
  "native_offset" : "0x00000"
 }
,
{
  "is_managed" : "false",
  "native_address" : "0x15323c918",
  "native_offset" : "0x00000"
 }
,
{
  "is_managed" : "false",
  "native_address" : "0x15323c6e0",
  "native_offset" : "0x00000"
 }
,
{
  "is_managed" : "false",
  "native_address" : "0x153145b70",
  "native_offset" : "0x00000"
 }
,
{
  "is_managed" : "false",
  "native_address" : "0x1900caa84",
  "native_offset" : "0x00000"
 }
,
{
  "is_managed" : "false",
  "native_address" : "0x15319490c",
  "native_offset" : "0x00000"
 }
,
{
  "is_managed" : "false",
  "native_address" : "0x15323d328",
  "native_offset" : "0x00000"
 }
,
{
  "is_managed" : "false",
  "native_address" : "0x15323d1d4",
  "native_offset" : "0x00000"
 }
,
{
  "is_managed" : "false",
  "native_address" : "0x1532bcc00",
  "native_offset" : "0x00000"
 }
,
{
  "is_managed" : "false",
  "native_address" : "0x1532bcb88",
  "native_offset" : "0x00000"
 }
,
{
  "is_managed" : "false",
  "native_address" : "0x19009bfa8",
  "native_offset" : "0x00000"
 }
,
{
  "is_managed" : "false",
  "native_address" : "0x190096da0",
  "native_offset" : "0x00000"
 }

]
},
{
"is_managed" : false,
"offset_free_hash" : "0x0",
"offset_rich_hash" : "0x0",
"crashed" : false,
"native_thread_id" : "0x178a3b000",
"thread_info_addr" : "0x1389d2200",
"thread_name" : "Finalizer",
"ctx" : {
  "IP" : "0x19005be90",
  "SP" : "0x178a3add0",
  "BP" : "0x178a3ae50"
},
"unmanaged_frames" : [
{
  "is_managed" : "false",
  "native_address" : "0x153104b5c",
  "native_offset" : "0x00000"
 }
,
{
  "is_managed" : "false",
  "native_address" : "0x15323c5bc",
  "native_offset" : "0x00000"
 }
,
{
  "is_managed" : "false",
  "native_address" : "0x15323c918",
  "native_offset" : "0x00000"
 }
,
{
  "is_managed" : "false",
  "native_address" : "0x15323c6e0",
  "native_offset" : "0x00000"
 }
,
{
  "is_managed" : "false",
  "native_address" : "0x153145b70",
  "native_offset" : "0x00000"
 }
,
{
  "is_managed" : "false",
  "native_address" : "0x1900caa84",
  "native_offset" : "0x00000"
 }
,
{
  "is_managed" : "false",
  "native_address" : "0x153276170",
  "native_offset" : "0x00000"
 }
,
{
  "is_managed" : "false",
  "native_address" : "0x15323d328",
  "native_offset" : "0x00000"
 }
,
{
  "is_managed" : "false",
  "native_address" : "0x15323d1d4",
  "native_offset" : "0x00000"
 }
,
{
  "is_managed" : "false",
  "native_address" : "0x1532bcc00",
  "native_offset" : "0x00000"
 }
,
{
  "is_managed" : "false",
  "native_address" : "0x1532bcb88",
  "native_offset" : "0x00000"
 }
,
{
  "is_managed" : "false",
  "native_address" : "0x19009bfa8",
  "native_offset" : "0x00000"
 }
,
{
  "is_managed" : "false",
  "native_address" : "0x190096da0",
  "native_offset" : "0x00000"
 }

]
},
{
"is_managed" : false,
"offset_free_hash" : "0x0",
"offset_rich_hash" : "0x0",
"crashed" : false,
"native_thread_id" : "0x17a413000",
"thread_info_addr" : "0x1390fba00",
"thread_name" : "Thread Pool I/O Selector",
"ctx" : {
  "IP" : "0x190066ff0",
  "SP" : "0x17a412ae0",
  "BP" : "0x17a412ce0"
},
"unmanaged_frames" : [
{
  "is_managed" : "false",
  "native_address" : "0x153104b5c",
  "native_offset" : "0x00000"
 }
,
{
  "is_managed" : "false",
  "native_address" : "0x15323c5bc",
  "native_offset" : "0x00000"
 }
,
{
  "is_managed" : "false",
  "native_address" : "0x15323c918",
  "native_offset" : "0x00000"
 }
,
{
  "is_managed" : "false",
  "native_address" : "0x15323c6e0",
  "native_offset" : "0x00000"
 }
,
{
  "is_managed" : "false",
  "native_address" : "0x153145b70",
  "native_offset" : "0x00000"
 }
,
{
  "is_managed" : "false",
  "native_address" : "0x1900caa84",
  "native_offset" : "0x00000"
 }
,
{
  "is_managed" : "false",
  "native_address" : "0x15328e7fc",
  "native_offset" : "0x00000"
 }
,
{
  "is_managed" : "false",
  "native_address" : "0x153241af8",
  "native_offset" : "0x00000"
 }
,
{
  "is_managed" : "false",
  "native_address" : "0x153241510",
  "native_offset" : "0x00000"
 }
,
{
  "is_managed" : "false",
  "native_address" : "0x15323d328",
  "native_offset" : "0x00000"
 }
,
{
  "is_managed" : "false",
  "native_address" : "0x15323d1d4",
  "native_offset" : "0x00000"
 }
,
{
  "is_managed" : "false",
  "native_address" : "0x1532bcc00",
  "native_offset" : "0x00000"
 }
,
{
  "is_managed" : "false",
  "native_address" : "0x1532bcb88",
  "native_offset" : "0x00000"
 }
,
{
  "is_managed" : "false",
  "native_address" : "0x19009bfa8",
  "native_offset" : "0x00000"
 }
,
{
  "is_managed" : "false",
  "native_address" : "0x190096da0",
  "native_offset" : "0x00000"
 }

]
}
]
}